duckstatsbomb/__about__.py
duckstatsbomb/__init__.py
duckstatsbomb/parser.py
duckstatsbomb/sql/cache/competitions/season_ids.sql
duckstatsbomb/sql/cache/competitions/v4/competitions.sql
duckstatsbomb/sql/cache/events/v4/events.sql
duckstatsbomb/sql/cache/events/v4/freeze_frames.sql
duckstatsbomb/sql/cache/events/v4/related_events.sql
duckstatsbomb/sql/cache/events/v4/tactics.sql
duckstatsbomb/sql/cache/events/v8/events.sql
duckstatsbomb/sql/cache/events/v8/freeze_frames.sql
duckstatsbomb/sql/cache/events/v8/related_events.sql
duckstatsbomb/sql/cache/events/v8/tactics.sql
duckstatsbomb/sql/cache/lineups/v2/lineup_players.sql
duckstatsbomb/sql/cache/lineups/v4/lineup_events.sql
duckstatsbomb/sql/cache/lineups/v4/lineup_formations.sql
duckstatsbomb/sql/cache/lineups/v4/lineup_players.sql
duckstatsbomb/sql/cache/lineups/v4/lineup_positions.sql
duckstatsbomb/sql/cache/matches/match_ids.sql
duckstatsbomb/sql/cache/matches/v3/matches.sql
duckstatsbomb/sql/cache/matches/v6/matches.sql
duckstatsbomb/sql/cache/threesixty/v1/freeze_frames.sql
duckstatsbomb/sql/cache/threesixty/v1/threesixty.sql
duckstatsbomb/sql/cache/threesixty/v2/freeze_frames.sql
duckstatsbomb/sql/cache/threesixty/v2/threesixty.sql
duckstatsbomb/sql/cache/threesixty/v2/visible_count.sql
duckstatsbomb/sql/cache/threesixty/v2/visible_distance.sql
duckstatsbomb/sql/original/competitions/season_ids.sql
duckstatsbomb/sql/original/competitions/v4/competitions.sql
duckstatsbomb/sql/original/events/v4/events.sql
duckstatsbomb/sql/original/events/v4/freeze_frames.sql
duckstatsbomb/sql/original/events/v4/related_events.sql
duckstatsbomb/sql/original/events/v4/tactics.sql
duckstatsbomb/sql/original/lineups/v2/lineup_players.sql
duckstatsbomb/sql/original/matches/match_ids.sql
duckstatsbomb/sql/original/matches/v3/matches.sql
duckstatsbomb/sql/original/threesixty/v1/freeze_frames.sql
duckstatsbomb/sql/original/threesixty/v1/threesixty.sql
duckstatsbomb-0.2.0.dist-info/METADATA
duckstatsbomb-0.2.0.dist-info/WHEEL
duckstatsbomb-0.2.0.dist-info/licenses/LICENSE
duckstatsbomb-0.2.0.dist-info/RECORD
