Metadata-Version: 2.4
Name: duckstatsbomb
Version: 0.2.0
Summary: A data parser for StatsBomb soccer data using duckdb
Project-URL: Documentation, https://github.com/andrewRowlinson/duckstatsbomb/blob/main/README.md
Project-URL: Issues, https://github.com/andrewRowlinson/duckstatsbomb/issues
Project-URL: Source, https://github.com/andrewRowlinson/duckstatsbomb
Author-email: Andrew Rowlinson <rowlinsonandy@gmail.com>
License-Expression: MIT
License-File: LICENSE
Keywords: football,soccer,statsbomb
Classifier: License :: OSI Approved :: MIT License
Requires-Dist: duckdb>=0.8
Requires-Dist: pandas
Requires-Dist: requests-cache
